mcp_fofa/__init__.py
mcp_fofa/__main__.py
mcp_fofa/server.py
mcp_fofa-0.1.0.dist-info/METADATA
mcp_fofa-0.1.0.dist-info/WHEEL
mcp_fofa-0.1.0.dist-info/entry_points.txt
mcp_fofa-0.1.0.dist-info/RECORD
