Metadata-Version: 2.4
Name: mcp_fofa
Version: 0.1.0
Summary: Add your description here
Requires-Python: >=3.11.13
Requires-Dist: build>=1.3.0
Requires-Dist: mcp[cli]>=1.12.4
Requires-Dist: requests>=2.32.4
Requires-Dist: twine>=6.1.0
